setup.py
profile_block/__init__.py
profile_block.egg-info/PKG-INFO
profile_block.egg-info/SOURCES.txt
profile_block.egg-info/dependency_links.txt
profile_block.egg-info/top_level.txt