Metadata-Version: 1.0
Name: profile-block
Version: 0.0.1
Summary: Provide a context manager to cProfile code
Home-page: https://github.com/sujaymansingh/profile_block
Author: Sujay Mansingh
Author-email: sujay.mansingh@gmail.com
License: LICENSE.txt
Platform: UNKNOWN
